{
  "version": 3,
  "middleware": {
    "/": {
      "files": [
        "server/edge-runtime-webpack.js",
        "server/middleware.js"
      ],
      "name": "middleware",
      "page": "/",
      "matchers": [
        {
          "regexp": "^(?:\\/(_next\\/data\\/[^/]{1,}))?(?:\\/((?!_next\\/static|_next\\/image|favicon.ico|.*\\.(?:svg|png|jpg|jpeg|gif|webp)$).*))(.json)?[\\/#\\?]?$",
          "originalSource": "/((?!_next/static|_next/image|favicon.ico|.*\\.(?:svg|png|jpg|jpeg|gif|webp)$).*)"
        }
      ],
      "wasm": [],
      "assets": [],
      "env": {
        "__NEXT_BUILD_ID": "4TZcnf1X4F621r_bqocj6",
        "NEXT_SERVER_ACTIONS_ENCRYPTION_KEY": "VJvYHaHXlmPUw9QM2WQjElC/HRSEDQBOoIqlhflKWCA=",
        "__NEXT_PREVIEW_MODE_ID": "189931bbc17dd071c7829517b53a721c",
        "__NEXT_PREVIEW_MODE_ENCRYPTION_KEY": "56400db4b81ca4ed4c78bf33f707b982da5b8c2ed9f48ed0cffd8f38cfd70db9",
        "__NEXT_PREVIEW_MODE_SIGNING_KEY": "1437d9ab8b1eafd8d7435c1723291281055add7b5320e0fbd9a5d2826d07dca5"
      }
    }
  },
  "functions": {},
  "sortedMiddleware": [
    "/"
  ]
}